AutoAdaptiveRobustRegression/AdaptiveRobustRegression.dll
AutoAdaptiveRobustRegression/__init__.py
AutoAdaptiveRobustRegression/internal.py
AutoAdaptiveRobustRegression/libopenblas.dll
AutoAdaptiveRobustRegression/linux/AdaptiveRobustRegression.so
AutoAdaptiveRobustRegression/linux/libopenblas.so
AutoAdaptiveRobustRegression-0.2.dist-info/LICENSE
AutoAdaptiveRobustRegression-0.2.dist-info/METADATA
AutoAdaptiveRobustRegression-0.2.dist-info/WHEEL
AutoAdaptiveRobustRegression-0.2.dist-info/top_level.txt
AutoAdaptiveRobustRegression-0.2.dist-info/RECORD
